QInfer-1.0.dist-info/DESCRIPTION.rst
QInfer-1.0.dist-info/METADATA
QInfer-1.0.dist-info/RECORD
QInfer-1.0.dist-info/WHEEL
QInfer-1.0.dist-info/metadata.json
QInfer-1.0.dist-info/top_level.txt
qinfer/__init__.py
qinfer/_exceptions.py
qinfer/abstract_model.py
qinfer/ale.py
qinfer/clustering.py
qinfer/config.py
qinfer/derived_models.py
qinfer/distributions.py
qinfer/domains.py
qinfer/expdesign.py
qinfer/finite_difference.py
qinfer/gpu_models.py
qinfer/ipy.py
qinfer/metrics.py
qinfer/parallel.py
qinfer/perf_testing.py
qinfer/rb.py
qinfer/resamplers.py
qinfer/score.py
qinfer/simple_est.py
qinfer/smc.py
qinfer/test_models.py
qinfer/unstructured_models.py
qinfer/utils.py
qinfer/version.py
qinfer/_lib/__init__.py
qinfer/_lib/docopt.py
qinfer/_lib/enum.py
qinfer/tomography/__init__.py
qinfer/tomography/bases.py
qinfer/tomography/distributions.py
qinfer/tomography/expdesign.py
qinfer/tomography/legacy.py
qinfer/tomography/models.py
qinfer/tomography/plotting_tools.py
