Metadata-Version: 2.0
Name: QInfer
Version: 1.0
Summary: Bayesian particle filtering for parameter estimation in quantum information applications.
Home-page: https://github.com/QInfer/python-qinfer
Author: Chris Granade and Chris Ferrie
Author-email: cgranade@cgranade.com
License: http://www.gnu.org/licenses/agpl-3.0.en.html
Download-URL: https://github.com/QInfer/python-qinfer/archive/v1.0b1.tar.gz
Keywords: quantum,Bayesian,estimation
Platform: any
Classifier: Development Status :: 4 - Beta
Classifier: Intended Audience :: Science/Research
Classifier: License :: OSI Approved :: GNU Affero General Public License v3
Classifier: Natural Language :: English
Classifier: Operating System :: OS Independent
Classifier: Programming Language :: Python :: 2.7
Classifier: Programming Language :: Python :: 3.3
Classifier: Programming Language :: Python :: 3.4
Classifier: Programming Language :: Python :: Implementation :: CPython
Classifier: Topic :: Scientific/Engineering :: Physics
Requires-Dist: future (>=0.15)
Requires-Dist: numpy
Requires-Dist: scipy
